{"type":"FeatureCollection","features":[{"type":"Feature","geometry":{"type":"Point","coordinates":[30.9385,45.378]},"properties":{"bright":"307.30","date":"2022/07/30","country_es":"Mundo"}},{"type":"Feature","geometry":{"type":"Point","coordinates":[24.4768,44.0787]},"properties":{"bright":"312.97","date":"2022/07/30","admin2":"Stoenești","admin3":"Olt","country_code":"RO","country_es":"Rumanía"}},{"type":"Feature","geometry":{"type":"Point","coordinates":[24.495,44.0769]},"properties":{"bright":"308.14","date":"2022/07/30","admin2":"Slăveni","admin3":"Olt","country_code":"RO","country_es":"Rumanía"}},{"type":"Feature","geometry":{"type":"Point","coordinates":[24.4905,44.0836]},"properties":{"bright":"308.76","date":"2022/07/30","admin2":"Stoenești","admin3":"Olt","country_code":"RO","country_es":"Rumanía"}},{"type":"Feature","geometry":{"type":"Point","coordinates":[24.4886,44.0729]},"properties":{"bright":"303.52","date":"2022/07/30","admin2":"Gostavățu","admin3":"Olt","country_code":"RO","country_es":"Rumanía"}},{"type":"Feature","geometry":{"type":"Point","coordinates":[24.9538,43.9616]},"properties":{"bright":"305.37","date":"2022/07/30","admin2":"Roșiorii de Vede","admin3":"Teleorman","country_code":"RO","country_es":"Rumanía"}},{"type":"Feature","geometry":{"type":"Point","coordinates":[29.4716,38.6316]},"properties":{"bright":"302.76","date":"2022/07/30","admin2":"Uşak Merkez","admin3":"Uşak","country_code":"TR","country_es":"Turquía"}},{"type":"Feature","geometry":{"type":"Point","coordinates":[4.5967,52.4863]},"properties":{"bright":"304.97","date":"2022/07/30","admin2":"Velsen","admin3":"Noord-Holland","country_code":"NL","country_es":"Países Bajos"}},{"type":"Feature","geometry":{"type":"Point","coordinates":[6.7179,51.4876]},"properties":{"bright":"324.55","date":"2022/07/30","admin2":"Duisburg","admin3":"Nordrhein-Westfalen","country_code":"DE","country_es":"Alemania"}},{"type":"Feature","geometry":{"type":"Point","coordinates":[6.7324,51.4856]},"properties":{"bright":"318.31","date":"2022/07/30","admin2":"Duisburg","admin3":"Nordrhein-Westfalen","country_code":"DE","country_es":"Alemania"}},{"type":"Feature","geometry":{"type":"Point","coordinates":[6.7158,51.3679]},"properties":{"bright":"311.94","date":"2022/07/30","admin2":"Duisburg","admin3":"Nordrhein-Westfalen","country_code":"DE","country_es":"Alemania"}},{"type":"Feature","geometry":{"type":"Point","coordinates":[3.8127,51.1789]},"properties":{"bright":"309.15","date":"2022/07/30","admin2":"Zelzate","admin3":"Oost-Vlaanderen","country_code":"BE","country_es":"Bélgica"}},{"type":"Feature","geometry":{"type":"Point","coordinates":[3.8101,51.1691]},"properties":{"bright":"303.24","date":"2022/07/30","admin2":"Gent","admin3":"Oost-Vlaanderen","country_code":"BE","country_es":"Bélgica"}},{"type":"Feature","geometry":{"type":"Point","coordinates":[6.8552,49.2452]},"properties":{"bright":"304.60","date":"2022/07/30","admin2":"Völklingen","admin3":"Saarland","country_code":"DE","country_es":"Alemania"}},{"type":"Feature","geometry":{"type":"Point","coordinates":[7.753,48.5633]},"properties":{"bright":"301.12","date":"2022/07/30","admin2":"Strasbourg","admin3":"Grand Est","country_code":"FR","country_es":"Francia"}},{"type":"Feature","geometry":{"type":"Point","coordinates":[-0.5045,47.5413]},"properties":{"bright":"301.58","date":"2022/07/30","admin2":"Angers","admin3":"Pays de la Loire","country_code":"FR","country_es":"Francia"}},{"type":"Feature","geometry":{"type":"Point","coordinates":[4.8854,43.4455]},"properties":{"bright":"305.52","date":"2022/07/30","admin2":"Fos-sur-Mer","admin3":"Provence-Alpes-Côte d'Azur","country_code":"FR","country_es":"Francia"}},{"type":"Feature","geometry":{"type":"Point","coordinates":[4.8976,43.4437]},"properties":{"bright":"308.83","date":"2022/07/30","admin2":"Fos-sur-Mer","admin3":"Provence-Alpes-Côte d'Azur","country_code":"FR","country_es":"Francia"}},{"type":"Feature","geometry":{"type":"Point","coordinates":[2.0903,41.3199]},"properties":{"bright":"303.02","date":"2022/07/30","admin2":"el Prat de Llobregat","admin3":"Barcelona","country_code":"ES","country_es":"España"}},{"type":"Feature","geometry":{"type":"Point","coordinates":[2.1031,41.3183]},"properties":{"bright":"303.73","date":"2022/07/30","admin2":"el Prat de Llobregat","admin3":"Barcelona","country_code":"ES","country_es":"España"}},{"type":"Feature","geometry":{"type":"Point","coordinates":[-7.4715,41.9023]},"properties":{"bright":"311.65","date":"2022/07/30","admin2":"Oímbra","admin3":"Ourense","country_code":"ES","country_es":"España"}},{"type":"Feature","geometry":{"type":"Point","coordinates":[-7.4752,41.9087]},"properties":{"bright":"310.55","date":"2022/07/30","admin2":"Oímbra","admin3":"Ourense","country_code":"ES","country_es":"España"}},{"type":"Feature","geometry":{"type":"Point","coordinates":[-4.9024,39.597]},"properties":{"bright":"305.31","date":"2022/07/30","admin2":"Robledo del Mazo","admin3":"Toledo","country_code":"ES","country_es":"España"}},{"type":"Feature","geometry":{"type":"Point","coordinates":[-4.9069,39.6008]},"properties":{"bright":"303.73","date":"2022/07/30","admin2":"Robledo del Mazo","admin3":"Toledo","country_code":"ES","country_es":"España"}},{"type":"Feature","geometry":{"type":"Point","coordinates":[19.5997,42.1889]},"properties":{"bright":"321.40","date":"2022/07/30","admin2":"Bashkia Malësi e Madhe","admin3":"Shqipëria Veriore","country_code":"AL","country_es":"Albania"}},{"type":"Feature","geometry":{"type":"Point","coordinates":[19.9816,40.5375]},"properties":{"bright":"321.42","date":"2022/07/30","admin2":"Bashkia Poliçan","admin3":"Shqipëria Jugore","country_code":"AL","country_es":"Albania"}},{"type":"Feature","geometry":{"type":"Point","coordinates":[15.7877,41.1627]},"properties":{"bright":"325.82","date":"2022/07/30","admin2":"Cerignola","admin3":"Puglia","country_code":"IT","country_es":"Italia"}},{"type":"Feature","geometry":{"type":"Point","coordinates":[15.9025,41.0617]},"properties":{"bright":"330.14","date":"2022/07/30","admin2":"Venosa","admin3":"Basilicata","country_code":"IT","country_es":"Italia"}},{"type":"Feature","geometry":{"type":"Point","coordinates":[15.709,41.0727]},"properties":{"bright":"327.09","date":"2022/07/30","admin2":"Melfi","admin3":"Basilicata","country_code":"IT","country_es":"Italia"}},{"type":"Feature","geometry":{"type":"Point","coordinates":[15.7208,41.071]},"properties":{"bright":"326.77","date":"2022/07/30","admin2":"Melfi","admin3":"Basilicata","country_code":"IT","country_es":"Italia"}},{"type":"Feature","geometry":{"type":"Point","coordinates":[15.9901,41.0203]},"properties":{"bright":"335.01","date":"2022/07/30","admin2":"Montemilone","admin3":"Basilicata","country_code":"IT","country_es":"Italia"}},{"type":"Feature","geometry":{"type":"Point","coordinates":[16.1405,40.9136]},"properties":{"bright":"333.39","date":"2022/07/30","admin2":"Genzano di Lucania","admin3":"Basilicata","country_code":"IT","country_es":"Italia"}},{"type":"Feature","geometry":{"type":"Point","coordinates":[17.8835,40.578]},"properties":{"bright":"331.60","date":"2022/07/30","admin2":"Brindisi","admin3":"Puglia","country_code":"IT","country_es":"Italia"}},{"type":"Feature","geometry":{"type":"Point","coordinates":[20.2002,39.96]},"properties":{"bright":"324.89","date":"2022/07/30","admin2":"Dropull i Poshtëm","admin3":"Shqipëria Jugore","country_code":"AL","country_es":"Albania"}},{"type":"Feature","geometry":{"type":"Point","coordinates":[20.2187,39.9563]},"properties":{"bright":"321.56","date":"2022/07/30","admin2":"Dropull i Poshtëm","admin3":"Shqipëria Jugore","country_code":"AL","country_es":"Albania"}},{"type":"Feature","geometry":{"type":"Point","coordinates":[20.1958,39.9496]},"properties":{"bright":"336.96","date":"2022/07/30","admin2":"Dropull i Poshtëm","admin3":"Shqipëria Jugore","country_code":"AL","country_es":"Albania"}},{"type":"Feature","geometry":{"type":"Point","coordinates":[20.1928,39.9578]},"properties":{"bright":"332.35","date":"2022/07/30","admin2":"Dropull i Poshtëm","admin3":"Shqipëria Jugore","country_code":"AL","country_es":"Albania"}},{"type":"Feature","geometry":{"type":"Point","coordinates":[20.211,39.9543]},"properties":{"bright":"327.19","date":"2022/07/30","admin2":"Dropull i Poshtëm","admin3":"Shqipëria Jugore","country_code":"AL","country_es":"Albania"}},{"type":"Feature","geometry":{"type":"Point","coordinates":[16.0485,38.5722]},"properties":{"bright":"328.88","date":"2022/07/30","admin2":"Mileto","admin3":"Calabria","country_code":"IT","country_es":"Italia"}},{"type":"Feature","geometry":{"type":"Point","coordinates":[16.2598,38.3069]},"properties":{"bright":"339.40","date":"2022/07/30","admin2":"Siderno","admin3":"Calabria","country_code":"IT","country_es":"Italia"}},{"type":"Feature","geometry":{"type":"Point","coordinates":[16.272,38.3049]},"properties":{"bright":"324.15","date":"2022/07/30","admin2":"Siderno","admin3":"Calabria","country_code":"IT","country_es":"Italia"}},{"type":"Feature","geometry":{"type":"Point","coordinates":[13.1687,38.6975]},"properties":{"bright":"317.24","date":"2022/07/30","admin2":"Ustica","admin3":"Sicilia","country_code":"IT","country_es":"Italia"}},{"type":"Feature","geometry":{"type":"Point","coordinates":[15.145,37.7801]},"properties":{"bright":"332.48","date":"2022/07/30","admin2":"Mascali","admin3":"Sicilia","country_code":"IT","country_es":"Italia"}},{"type":"Feature","geometry":{"type":"Point","coordinates":[12.8431,37.8026]},"properties":{"bright":"330.42","date":"2022/07/30","admin2":"Salemi","admin3":"Sicilia","country_code":"IT","country_es":"Italia"}},{"type":"Feature","geometry":{"type":"Point","coordinates":[13.3498,37.502]},"properties":{"bright":"330.28","date":"2022/07/30","admin2":"Calamonaci","admin3":"Sicilia","country_code":"IT","country_es":"Italia"}},{"type":"Feature","geometry":{"type":"Point","coordinates":[13.5214,37.3671]},"properties":{"bright":"331.46","date":"2022/07/30","admin2":"Agrigento","admin3":"Sicilia","country_code":"IT","country_es":"Italia"}},{"type":"Feature","geometry":{"type":"Point","coordinates":[14.1777,37.1972]},"properties":{"bright":"331.78","date":"2022/07/30","admin2":"Butera","admin3":"Sicilia","country_code":"IT","country_es":"Italia"}},{"type":"Feature","geometry":{"type":"Point","coordinates":[25.3279,56.4577]},"properties":{"bright":"307.81","date":"2022/07/30","admin3":"Zemgale","country_code":"LV","country_es":"Letonia"}},{"type":"Feature","geometry":{"type":"Point","coordinates":[23.2569,44.0057]},"properties":{"bright":"327.95","date":"2022/07/30","admin2":"Băilești","admin3":"Dolj","country_code":"RO","country_es":"Rumanía"}},{"type":"Feature","geometry":{"type":"Point","coordinates":[23.2781,44.0012]},"properties":{"bright":"343.34","date":"2022/07/30","admin2":"Băilești","admin3":"Dolj","country_code":"RO","country_es":"Rumanía"}},{"type":"Feature","geometry":{"type":"Point","coordinates":[27.6828,38.1515]},"properties":{"bright":"326.36","date":"2022/07/30","admin2":"Bayındır","admin3":"İzmir","country_code":"TR","country_es":"Turquía"}},{"type":"Feature","geometry":{"type":"Point","coordinates":[32.6161,41.1833]},"properties":{"bright":"326.76","date":"2022/07/30","admin2":"Karabük","admin3":"Karabük","country_code":"TR","country_es":"Turquía"}},{"type":"Feature","geometry":{"type":"Point","coordinates":[20.205,39.9538]},"properties":{"bright":"327.24","date":"2022/07/30","admin2":"Dropull i Poshtëm","admin3":"Shqipëria Jugore","country_code":"AL","country_es":"Albania"}},{"type":"Feature","geometry":{"type":"Point","coordinates":[20.1759,39.9474]},"properties":{"bright":"321.75","date":"2022/07/30","admin2":"Bashkia Finiq","admin3":"Shqipëria Jugore","country_code":"AL","country_es":"Albania"}},{"type":"Feature","geometry":{"type":"Point","coordinates":[19.9868,40.5388]},"properties":{"bright":"351.74","date":"2022/07/30","admin2":"Bashkia Poliçan","admin3":"Shqipëria Jugore","country_code":"AL","country_es":"Albania"}},{"type":"Feature","geometry":{"type":"Point","coordinates":[19.9612,40.5331]},"properties":{"bright":"331.10","date":"2022/07/30","admin2":"Bashkia Poliçan","admin3":"Shqipëria Jugore","country_code":"AL","country_es":"Albania"}},{"type":"Feature","geometry":{"type":"Point","coordinates":[15.9055,41.0656]},"properties":{"bright":"324.97","date":"2022/07/30","admin2":"Montemilone","admin3":"Basilicata","country_code":"IT","country_es":"Italia"}},{"type":"Feature","geometry":{"type":"Point","coordinates":[25.5601,43.893]},"properties":{"bright":"334.62","date":"2022/07/30","admin2":"Ștorobăneasa","admin3":"Teleorman","country_code":"RO","country_es":"Rumanía"}},{"type":"Feature","geometry":{"type":"Point","coordinates":[25.5573,43.9019]},"properties":{"bright":"331.94","date":"2022/07/30","admin2":"Valea Părului","admin3":"Teleorman","country_code":"RO","country_es":"Rumanía"}},{"type":"Feature","geometry":{"type":"Point","coordinates":[24.4702,43.7766]},"properties":{"bright":"336.22","date":"2022/07/30","admin2":"Corabia","admin3":"Olt","country_code":"RO","country_es":"Rumanía"}},{"type":"Feature","geometry":{"type":"Point","coordinates":[24.1331,43.811]},"properties":{"bright":"334.21","date":"2022/07/30","admin2":"Dăbuleni","admin3":"Dolj","country_code":"RO","country_es":"Rumanía"}},{"type":"Feature","geometry":{"type":"Point","coordinates":[28.9761,44.9672]},"properties":{"bright":"311.37","date":"2022/07/30","admin2":"Valea Nucarilor","admin3":"Tulcea","country_code":"RO","country_es":"Rumanía"}},{"type":"Feature","geometry":{"type":"Point","coordinates":[25.9145,45.0358]},"properties":{"bright":"321.83","date":"2022/07/30","admin2":"Băicoi","admin3":"Prahova","country_code":"RO","country_es":"Rumanía"}},{"type":"Feature","geometry":{"type":"Point","coordinates":[-8.4421,43.3301]},"properties":{"bright":"317.51","date":"2022/07/30","admin2":"A Coruña","admin3":"Galicia","country_code":"ES","country_es":"España"}},{"type":"Feature","geometry":{"type":"Point","coordinates":[-6.9528,42.7512]},"properties":{"bright":"322.77","date":"2022/07/30","admin2":"Balboa","admin3":"León","country_code":"ES","country_es":"España"}},{"type":"Feature","geometry":{"type":"Point","coordinates":[-6.853,42.7251]},"properties":{"bright":"317.97","date":"2022/07/30","admin2":"Villafranca del Bierzo","admin3":"León","country_code":"ES","country_es":"España"}},{"type":"Feature","geometry":{"type":"Point","coordinates":[-8.2984,42.1402]},"properties":{"bright":"320.74","date":"2022/07/30","admin2":"Arbo","admin3":"Pontevedra","country_code":"ES","country_es":"España"}},{"type":"Feature","geometry":{"type":"Point","coordinates":[-8.3255,42.1351]},"properties":{"bright":"394.04","date":"2022/07/30","admin2":"Arbo","admin3":"Pontevedra","country_code":"ES","country_es":"España"}},{"type":"Feature","geometry":{"type":"Point","coordinates":[-8.3133,42.1332]},"properties":{"bright":"416.47","date":"2022/07/30","admin2":"Arbo","admin3":"Pontevedra","country_code":"ES","country_es":"España"}},{"type":"Feature","geometry":{"type":"Point","coordinates":[-8.3009,42.1313]},"properties":{"bright":"333.94","date":"2022/07/30","admin2":"Arbo","admin3":"Pontevedra","country_code":"ES","country_es":"España"}},{"type":"Feature","geometry":{"type":"Point","coordinates":[-8.3277,42.1261]},"properties":{"bright":"461.08","date":"2022/07/30","admin2":"Arbo","admin3":"Pontevedra","country_code":"ES","country_es":"España"}},{"type":"Feature","geometry":{"type":"Point","coordinates":[-8.3156,42.1243]},"properties":{"bright":"422.51","date":"2022/07/30","admin2":"Arbo","admin3":"Pontevedra","country_code":"ES","country_es":"España"}},{"type":"Feature","geometry":{"type":"Point","coordinates":[-8.2911,42.1205]},"properties":{"bright":"319.45","date":"2022/07/30","admin2":"Arbo","admin3":"Pontevedra","country_code":"ES","country_es":"España"}},{"type":"Feature","geometry":{"type":"Point","coordinates":[-8.33,42.1172]},"properties":{"bright":"360.21","date":"2022/07/30","admin2":"Arbo","admin3":"Pontevedra","country_code":"ES","country_es":"España"}},{"type":"Feature","geometry":{"type":"Point","coordinates":[-8.3178,42.1153]},"properties":{"bright":"334.44","date":"2022/07/30","admin2":"Arbo","admin3":"Pontevedra","country_code":"ES","country_es":"España"}},{"type":"Feature","geometry":{"type":"Point","coordinates":[13.3512,37.5031]},"properties":{"bright":"331.60","date":"2022/07/30","admin2":"Calamonaci","admin3":"Sicilia","country_code":"IT","country_es":"Italia"}},{"type":"Feature","geometry":{"type":"Point","coordinates":[13.3443,37.4986]},"properties":{"bright":"328.40","date":"2022/07/30","admin2":"Calamonaci","admin3":"Sicilia","country_code":"IT","country_es":"Italia"}},{"type":"Feature","geometry":{"type":"Point","coordinates":[16.4192,38.3459]},"properties":{"bright":"319.13","date":"2022/07/30","admin2":"Caulonia","admin3":"Calabria","country_code":"IT","country_es":"Italia"}},{"type":"Feature","geometry":{"type":"Point","coordinates":[16.3751,38.344]},"properties":{"bright":"359.18","date":"2022/07/30","admin2":"Roccella Ionica","admin3":"Calabria","country_code":"IT","country_es":"Italia"}},{"type":"Feature","geometry":{"type":"Point","coordinates":[16.4107,38.3532]},"properties":{"bright":"323.72","date":"2022/07/30","admin2":"Caulonia","admin3":"Calabria","country_code":"IT","country_es":"Italia"}},{"type":"Feature","geometry":{"type":"Point","coordinates":[16.366,38.3515]},"properties":{"bright":"330.80","date":"2022/07/30","admin2":"Roccella Ionica","admin3":"Calabria","country_code":"IT","country_es":"Italia"}},{"type":"Feature","geometry":{"type":"Point","coordinates":[15.8397,39.942]},"properties":{"bright":"328.07","date":"2022/07/30","admin2":"Aieta","admin3":"Calabria","country_code":"IT","country_es":"Italia"}},{"type":"Feature","geometry":{"type":"Point","coordinates":[15.8024,39.9404]},"properties":{"bright":"313.85","date":"2022/07/30","admin2":"Tortora","admin3":"Calabria","country_code":"IT","country_es":"Italia"}},{"type":"Feature","geometry":{"type":"Point","coordinates":[15.8342,39.9349]},"properties":{"bright":"321.43","date":"2022/07/30","admin2":"Aieta","admin3":"Calabria","country_code":"IT","country_es":"Italia"}},{"type":"Feature","geometry":{"type":"Point","coordinates":[15.833,39.9511]},"properties":{"bright":"318.51","date":"2022/07/30","admin2":"Tortora","admin3":"Calabria","country_code":"IT","country_es":"Italia"}},{"type":"Feature","geometry":{"type":"Point","coordinates":[-0.5971,38.3654]},"properties":{"bright":"320.74","date":"2022/07/30","admin2":"Alacant / Alicante","admin3":"Alacant / Alicante","country_code":"ES","country_es":"España"}},{"type":"Feature","geometry":{"type":"Point","coordinates":[-0.613,38.3624]},"properties":{"bright":"322.08","date":"2022/07/30","admin2":"Alacant / Alicante","admin3":"Alacant / Alicante","country_code":"ES","country_es":"España"}},{"type":"Feature","geometry":{"type":"Point","coordinates":[4.893,43.4486]},"properties":{"bright":"328.90","date":"2022/07/30","admin2":"Fos-sur-Mer","admin3":"Provence-Alpes-Côte d'Azur","country_code":"FR","country_es":"Francia"}},{"type":"Feature","geometry":{"type":"Point","coordinates":[4.664,43.9616]},"properties":{"bright":"327.71","date":"2022/07/30","admin2":"Nîmes","admin3":"Occitanie","country_code":"FR","country_es":"Francia"}},{"type":"Feature","geometry":{"type":"Point","coordinates":[4.6509,43.96]},"properties":{"bright":"327.54","date":"2022/07/30","admin2":"Nîmes","admin3":"Occitanie","country_code":"FR","country_es":"Francia"}},{"type":"Feature","geometry":{"type":"Point","coordinates":[-8.325,42.117]},"properties":{"bright":"332.18","date":"2022/07/30","admin2":"Arbo","admin3":"Pontevedra","country_code":"ES","country_es":"España"}},{"type":"Feature","geometry":{"type":"Point","coordinates":[-8.3279,42.1323]},"properties":{"bright":"334.89","date":"2022/07/30","admin2":"Arbo","admin3":"Pontevedra","country_code":"ES","country_es":"España"}},{"type":"Feature","geometry":{"type":"Point","coordinates":[-8.3278,42.1148]},"properties":{"bright":"325.50","date":"2022/07/30","admin2":"Arbo","admin3":"Pontevedra","country_code":"ES","country_es":"España"}},{"type":"Feature","geometry":{"type":"Point","coordinates":[-8.2977,42.1386]},"properties":{"bright":"314.91","date":"2022/07/30","admin2":"Arbo","admin3":"Pontevedra","country_code":"ES","country_es":"España"}},{"type":"Feature","geometry":{"type":"Point","coordinates":[-8.3305,42.1302]},"properties":{"bright":"339.11","date":"2022/07/30","admin2":"Arbo","admin3":"Pontevedra","country_code":"ES","country_es":"España"}},{"type":"Feature","geometry":{"type":"Point","coordinates":[5.0205,45.668]},"properties":{"bright":"327.90","date":"2022/07/30","admin2":"Lyon","admin3":"Circonscription départementale du Rhône","country_code":"FR","country_es":"Francia"}},{"type":"Feature","geometry":{"type":"Point","coordinates":[0.4668,46.4177]},"properties":{"bright":"326.42","date":"2022/07/30","admin2":"Poitiers","admin3":"Nouvelle-Aquitaine","country_code":"FR","country_es":"Francia"}},{"type":"Feature","geometry":{"type":"Point","coordinates":[6.7353,51.4913]},"properties":{"bright":"310.64","date":"2022/07/30","admin2":"Duisburg","admin3":"Nordrhein-Westfalen","country_code":"DE","country_es":"Alemania"}},{"type":"Feature","geometry":{"type":"Point","coordinates":[14.1924,37.2045]},"properties":{"bright":"328.41","date":"2022/07/30","admin2":"Butera","admin3":"Sicilia","country_code":"IT","country_es":"Italia"}},{"type":"Feature","geometry":{"type":"Point","coordinates":[14.1842,37.2092]},"properties":{"bright":"329.78","date":"2022/07/30","admin2":"Butera","admin3":"Sicilia","country_code":"IT","country_es":"Italia"}},{"type":"Feature","geometry":{"type":"Point","coordinates":[14.2597,37.3172]},"properties":{"bright":"381.50","date":"2022/07/30","admin2":"Mazzarino","admin3":"Sicilia","country_code":"IT","country_es":"Italia"}},{"type":"Feature","geometry":{"type":"Point","coordinates":[14.2294,37.3152]},"properties":{"bright":"336.78","date":"2022/07/30","admin2":"Mazzarino","admin3":"Sicilia","country_code":"IT","country_es":"Italia"}},{"type":"Feature","geometry":{"type":"Point","coordinates":[13.5091,37.3711]},"properties":{"bright":"329.52","date":"2022/07/30","admin2":"Agrigento","admin3":"Sicilia","country_code":"IT","country_es":"Italia"}},{"type":"Feature","geometry":{"type":"Point","coordinates":[23.7136,50.3984]},"properties":{"bright":"325.27","date":"2022/07/30","admin2":"gmina Ulhówek","admin3":"województwo lubelskie","country_code":"PL","country_es":"Polonia"}},{"type":"Feature","geometry":{"type":"Point","coordinates":[23.6997,50.3962]},"properties":{"bright":"324.89","date":"2022/07/30","admin2":"gmina Lubycza Królewska","admin3":"województwo lubelskie","country_code":"PL","country_es":"Polonia"}},{"type":"Feature","geometry":{"type":"Point","coordinates":[26.4293,55.1444]},"properties":{"bright":"308.43","date":"2022/07/30","admin2":"Valiukiškė","admin3":"Švenčionių rajono savivaldybė","country_code":"LT","country_es":"Lituania"}},{"type":"Feature","geometry":{"type":"Point","coordinates":[12.7312,56.1209]},"properties":{"bright":"308.12","date":"2022/07/30","admin2":"Helsingborgs kommun","admin3":"Skåne län","country_code":"SE","country_es":"Suecia"}},{"type":"Feature","geometry":{"type":"Point","coordinates":[24.3147,58.5896]},"properties":{"bright":"301.47","date":"2022/07/30","admin2":"Põhja-Pärnumaa vald","admin3":"Pärnu maakond","country_code":"EE","country_es":"Estonia"}},{"type":"Feature","geometry":{"type":"Point","coordinates":[15.5838,57.6133]},"properties":{"bright":"302.84","date":"2022/07/30","admin2":"Eksjö kommun","admin3":"Jönköpings län","country_code":"SE","country_es":"Suecia"}},{"type":"Feature","geometry":{"type":"Point","coordinates":[17.4556,62.5245]},"properties":{"bright":"300.13","date":"2022/07/30","admin2":"Hässjö distrikt","admin3":"Västernorrlands län","country_code":"SE","country_es":"Suecia"}},{"type":"Feature","geometry":{"type":"Point","coordinates":[-8.1152,40.0328]},"properties":{"bright":"342.80","date":"2022/07/30","admin2":"Góis","admin3":"Coimbra","country_code":"PT","country_es":"Portugal"}},{"type":"Feature","geometry":{"type":"Point","coordinates":[-7.5658,41.4514]},"properties":{"bright":"349.62","date":"2022/07/30","admin2":"Vila Pouca de Aguiar","admin3":"Vila Real","country_code":"PT","country_es":"Portugal"}},{"type":"Feature","geometry":{"type":"Point","coordinates":[-7.5752,41.4531]},"properties":{"bright":"350.33","date":"2022/07/30","admin2":"Vila Pouca de Aguiar","admin3":"Vila Real","country_code":"PT","country_es":"Portugal"}},{"type":"Feature","geometry":{"type":"Point","coordinates":[-8.3128,42.1204]},"properties":{"bright":"333.33","date":"2022/07/30","admin2":"Arbo","admin3":"Pontevedra","country_code":"ES","country_es":"España"}},{"type":"Feature","geometry":{"type":"Point","coordinates":[-8.3651,42.1187]},"properties":{"bright":"328.56","date":"2022/07/30","admin2":"As Neves","admin3":"Pontevedra","country_code":"ES","country_es":"España"}},{"type":"Feature","geometry":{"type":"Point","coordinates":[-8.324,42.1252]},"properties":{"bright":"338.38","date":"2022/07/30","admin2":"Arbo","admin3":"Pontevedra","country_code":"ES","country_es":"España"}},{"type":"Feature","geometry":{"type":"Point","coordinates":[-8.3753,42.1237]},"properties":{"bright":"323.00","date":"2022/07/30","admin2":"As Neves","admin3":"Pontevedra","country_code":"ES","country_es":"España"}},{"type":"Feature","geometry":{"type":"Point","coordinates":[13.3822,37.377]},"properties":{"bright":"311.18","date":"2022/07/30","admin2":"Montallegro","admin3":"Sicilia","country_code":"IT","country_es":"Italia"}},{"type":"Feature","geometry":{"type":"Point","coordinates":[13.2593,37.5138]},"properties":{"bright":"309.32","date":"2022/07/30","admin2":"Ribera","admin3":"Sicilia","country_code":"IT","country_es":"Italia"}},{"type":"Feature","geometry":{"type":"Point","coordinates":[13.247,37.5118]},"properties":{"bright":"314.16","date":"2022/07/30","admin2":"Ribera","admin3":"Sicilia","country_code":"IT","country_es":"Italia"}},{"type":"Feature","geometry":{"type":"Point","coordinates":[16.0766,39.2219]},"properties":{"bright":"305.39","date":"2022/07/30","admin2":"San Biase","admin3":"Calabria","country_code":"IT","country_es":"Italia"}},{"type":"Feature","geometry":{"type":"Point","coordinates":[16.0652,39.2204]},"properties":{"bright":"313.88","date":"2022/07/30","admin2":"Longobardi","admin3":"Calabria","country_code":"IT","country_es":"Italia"}},{"type":"Feature","geometry":{"type":"Point","coordinates":[16.0745,39.2309]},"properties":{"bright":"304.26","date":"2022/07/30","admin2":"San Biase","admin3":"Calabria","country_code":"IT","country_es":"Italia"}},{"type":"Feature","geometry":{"type":"Point","coordinates":[20.2395,39.9493]},"properties":{"bright":"311.25","date":"2022/07/30","admin2":"Dropull i Poshtëm","admin3":"Shqipëria Jugore","country_code":"AL","country_es":"Albania"}},{"type":"Feature","geometry":{"type":"Point","coordinates":[20.2191,39.9472]},"properties":{"bright":"304.53","date":"2022/07/30","admin2":"Dropull i Poshtëm","admin3":"Shqipëria Jugore","country_code":"AL","country_es":"Albania"}},{"type":"Feature","geometry":{"type":"Point","coordinates":[20.2327,39.9514]},"properties":{"bright":"311.85","date":"2022/07/30","admin2":"Dropull i Poshtëm","admin3":"Shqipëria Jugore","country_code":"AL","country_es":"Albania"}},{"type":"Feature","geometry":{"type":"Point","coordinates":[16.2227,39.6553]},"properties":{"bright":"306.91","date":"2022/07/30","admin2":"Roggiano Gravina","admin3":"Calabria","country_code":"IT","country_es":"Italia"}},{"type":"Feature","geometry":{"type":"Point","coordinates":[19.9768,40.5384]},"properties":{"bright":"307.58","date":"2022/07/30","admin2":"Bashkia Poliçan","admin3":"Shqipëria Jugore","country_code":"AL","country_es":"Albania"}},{"type":"Feature","geometry":{"type":"Point","coordinates":[19.9588,40.5367]},"properties":{"bright":"305.10","date":"2022/07/30","admin2":"Bashkia Poliçan","admin3":"Shqipëria Jugore","country_code":"AL","country_es":"Albania"}},{"type":"Feature","geometry":{"type":"Point","coordinates":[4.8856,43.4482]},"properties":{"bright":"308.65","date":"2022/07/30","admin2":"Fos-sur-Mer","admin3":"Provence-Alpes-Côte d'Azur","country_code":"FR","country_es":"Francia"}},{"type":"Feature","geometry":{"type":"Point","coordinates":[-7.0336,40.9817]},"properties":{"bright":"313.14","date":"2022/07/30","admin2":"Almendra","admin3":"Guarda","country_code":"PT","country_es":"Portugal"}},{"type":"Feature","geometry":{"type":"Point","coordinates":[-8.3036,42.1238]},"properties":{"bright":"349.73","date":"2022/07/30","admin2":"Arbo","admin3":"Pontevedra","country_code":"ES","country_es":"España"}},{"type":"Feature","geometry":{"type":"Point","coordinates":[-8.3169,42.1222]},"properties":{"bright":"376.22","date":"2022/07/30","admin2":"Arbo","admin3":"Pontevedra","country_code":"ES","country_es":"España"}},{"type":"Feature","geometry":{"type":"Point","coordinates":[-8.3297,42.1206]},"properties":{"bright":"328.63","date":"2022/07/30","admin2":"Arbo","admin3":"Pontevedra","country_code":"ES","country_es":"España"}},{"type":"Feature","geometry":{"type":"Point","coordinates":[-8.3324,42.1298]},"properties":{"bright":"305.63","date":"2022/07/30","admin2":"Arbo","admin3":"Pontevedra","country_code":"ES","country_es":"España"}},{"type":"Feature","geometry":{"type":"Point","coordinates":[-8.5478,42.2111]},"properties":{"bright":"310.14","date":"2022/07/30","admin2":"Ponteareas","admin3":"Pontevedra","country_code":"ES","country_es":"España"}},{"type":"Feature","geometry":{"type":"Point","coordinates":[-8.5368,42.2219]},"properties":{"bright":"312.96","date":"2022/07/30","admin2":"Ponteareas","admin3":"Pontevedra","country_code":"ES","country_es":"España"}},{"type":"Feature","geometry":{"type":"Point","coordinates":[-8.5501,42.2203]},"properties":{"bright":"328.95","date":"2022/07/30","admin2":"Ponteareas","admin3":"Pontevedra","country_code":"ES","country_es":"España"}},{"type":"Feature","geometry":{"type":"Point","coordinates":[-7.724,42.6611]},"properties":{"bright":"319.25","date":"2022/07/30","admin2":"O Saviñao","admin3":"Lugo","country_code":"ES","country_es":"España"}},{"type":"Feature","geometry":{"type":"Point","coordinates":[-7.7376,42.6595]},"properties":{"bright":"311.48","date":"2022/07/30","admin2":"Chantada","admin3":"Lugo","country_code":"ES","country_es":"España"}},{"type":"Feature","geometry":{"type":"Point","coordinates":[19.9757,40.5375]},"properties":{"bright":"301.67","date":"2022/07/31","admin2":"Bashkia Poliçan","admin3":"Shqipëria Jugore","country_code":"AL","country_es":"Albania"}},{"type":"Feature","geometry":{"type":"Point","coordinates":[16.0715,39.2309]},"properties":{"bright":"312.91","date":"2022/07/31","admin2":"San Biase","admin3":"Calabria","country_code":"IT","country_es":"Italia"}},{"type":"Feature","geometry":{"type":"Point","coordinates":[13.5071,37.3721]},"properties":{"bright":"305.80","date":"2022/07/31","admin2":"Agrigento","admin3":"Sicilia","country_code":"IT","country_es":"Italia"}},{"type":"Feature","geometry":{"type":"Point","coordinates":[16.4788,59.3835]},"properties":{"bright":"302.26","date":"2022/07/31","admin2":"Eskilstuna","admin3":"Södermanlands län","country_code":"SE","country_es":"Suecia"}},{"type":"Feature","geometry":{"type":"Point","coordinates":[-8.2454,42.2331]},"properties":{"bright":"304.39","date":"2022/07/31","admin2":"A Cañiza","admin3":"Pontevedra","country_code":"ES","country_es":"España"}},{"type":"Feature","geometry":{"type":"Point","coordinates":[-8.2478,42.224]},"properties":{"bright":"338.00","date":"2022/07/31","admin2":"Melón","admin3":"Ourense","country_code":"ES","country_es":"España"}},{"type":"Feature","geometry":{"type":"Point","coordinates":[-8.2352,42.2223]},"properties":{"bright":"309.82","date":"2022/07/31","admin2":"A Cañiza","admin3":"Pontevedra","country_code":"ES","country_es":"España"}},{"type":"Feature","geometry":{"type":"Point","coordinates":[-8.3406,42.1338]},"properties":{"bright":"305.06","date":"2022/07/31","admin2":"Arbo","admin3":"Pontevedra","country_code":"ES","country_es":"España"}},{"type":"Feature","geometry":{"type":"Point","coordinates":[-8.3279,42.1322]},"properties":{"bright":"304.02","date":"2022/07/31","admin2":"Arbo","admin3":"Pontevedra","country_code":"ES","country_es":"España"}},{"type":"Feature","geometry":{"type":"Point","coordinates":[-8.303,42.129]},"properties":{"bright":"303.13","date":"2022/07/31","admin2":"Arbo","admin3":"Pontevedra","country_code":"ES","country_es":"España"}},{"type":"Feature","geometry":{"type":"Point","coordinates":[-8.3052,42.1198]},"properties":{"bright":"305.96","date":"2022/07/31","admin2":"Arbo","admin3":"Pontevedra","country_code":"ES","country_es":"España"}},{"type":"Feature","geometry":{"type":"Point","coordinates":[-7.0425,40.9819]},"properties":{"bright":"341.95","date":"2022/07/31","admin2":"Almendra","admin3":"Guarda","country_code":"PT","country_es":"Portugal"}},{"type":"Feature","geometry":{"type":"Point","coordinates":[-7.0308,40.9802]},"properties":{"bright":"326.62","date":"2022/07/31","admin2":"Almendra","admin3":"Guarda","country_code":"PT","country_es":"Portugal"}},{"type":"Feature","geometry":{"type":"Point","coordinates":[-7.0447,40.973]},"properties":{"bright":"333.52","date":"2022/07/31","admin2":"Figueira de Castelo Rodrigo","admin3":"Guarda","country_code":"PT","country_es":"Portugal"}},{"type":"Feature","geometry":{"type":"Point","coordinates":[34.3961,46.9065]},"properties":{"bright":"306.14","date":"2022/07/30","admin2":"Rogach superior","admin3":"Región de Kherson","country_code":"UA","country_es":"Ucrania"}},{"type":"Feature","geometry":{"type":"Point","coordinates":[34.4106,46.904]},"properties":{"bright":"313.77","date":"2022/07/30","admin2":"Comunidad de la ciudad de Syrogorod Lower","admin3":"Región de Kherson","country_code":"UA","country_es":"Ucrania"}},{"type":"Feature","geometry":{"type":"Point","coordinates":[24.1739,42.7172]},"properties":{"bright":"304.24","date":"2022/07/30","admin2":"Pirgot","admin3":"Sofía","country_code":"BG","country_es":"Bulgaria"}},{"type":"Feature","geometry":{"type":"Point","coordinates":[-0.2595,35.8124]},"properties":{"bright":"307.75","date":"2022/07/30","admin2":"Bethioua ⴱⴻⵟⵟⵉⵡⴰ Bataya","admin3":"Oran ⵡⴻⵀⵔⴰⵏ Oran","country_code":"DZ","country_es":"Argelia"}},{"type":"Feature","geometry":{"type":"Point","coordinates":[-0.2467,35.8108]},"properties":{"bright":"309.88","date":"2022/07/30","admin2":"Bethioua ⴱⴻⵟⵟⵉⵡⴰ Bataya","admin3":"Oran ⵡⴻⵀⵔⴰⵏ Oran","country_code":"DZ","country_es":"Argelia"}},{"type":"Feature","geometry":{"type":"Point","coordinates":[33.012,47.8421]},"properties":{"bright":"317.87","date":"2022/07/30","admin2":"Comunidad de asentamiento de Kazanka","admin3":"Región mykolaiv","country_code":"UA","country_es":"Ucrania"}},{"type":"Feature","geometry":{"type":"Point","coordinates":[34.6131,47.2385]},"properties":{"bright":"323.48","date":"2022/07/30","admin2":"La gran comunidad rural de Bilozersk","admin3":"Región de Zaporizhzhia","country_code":"UA","country_es":"Ucrania"}},{"type":"Feature","geometry":{"type":"Point","coordinates":[34.606,47.2303]},"properties":{"bright":"322.28","date":"2022/07/30","admin2":"La gran comunidad rural de Bilozersk","admin3":"Región de Zaporizhzhia","country_code":"UA","country_es":"Ucrania"}},{"type":"Feature","geometry":{"type":"Point","coordinates":[34.76,47.2057]},"properties":{"bright":"321.89","date":"2022/07/30","admin2":"La gran comunidad rural de Bilozersk","admin3":"Región de Zaporizhzhia","country_code":"UA","country_es":"Ucrania"}},{"type":"Feature","geometry":{"type":"Point","coordinates":[34.7341,47.1847]},"properties":{"bright":"326.70","date":"2022/07/30","admin2":"La gran comunidad rural de Bilozersk","admin3":"Región de Zaporizhzhia","country_code":"UA","country_es":"Ucrania"}},{"type":"Feature","geometry":{"type":"Point","coordinates":[32.8658,47.26]},"properties":{"bright":"320.49","date":"2022/07/30","admin2":"Comunidad de asentamiento de Berezneguatsky","admin3":"Región mykolaiv","country_code":"UA","country_es":"Ucrania"}},{"type":"Feature","geometry":{"type":"Point","coordinates":[34.7022,47.0388]},"properties":{"bright":"326.21","date":"2022/07/30","admin2":"Comunidad de Chkalovsk Village","admin3":"Región de Zaporizhzhia","country_code":"UA","country_es":"Ucrania"}},{"type":"Feature","geometry":{"type":"Point","coordinates":[34.6966,47.0414]},"properties":{"bright":"328.72","date":"2022/07/30","admin2":"Comunidad de Chkalovsk Village","admin3":"Región de Zaporizhzhia","country_code":"UA","country_es":"Ucrania"}},{"type":"Feature","geometry":{"type":"Point","coordinates":[34.401,47.0426]},"properties":{"bright":"327.07","date":"2022/07/30","admin2":"Comunidad de la ciudad de Syrogorod Lower","admin3":"Región de Kherson","country_code":"UA","country_es":"Ucrania"}},{"type":"Feature","geometry":{"type":"Point","coordinates":[34.1184,47.0413]},"properties":{"bright":"322.43","date":"2022/07/30","admin2":"Velikolepetian Settlement Community","admin3":"Región de Kherson","country_code":"UA","country_es":"Ucrania"}},{"type":"Feature","geometry":{"type":"Point","coordinates":[34.142,47.0395]},"properties":{"bright":"331.78","date":"2022/07/30","admin2":"Comunidad rural de Rubanivska","admin3":"Región de Kherson","country_code":"UA","country_es":"Ucrania"}},{"type":"Feature","geometry":{"type":"Point","coordinates":[34.1383,47.0159]},"properties":{"bright":"325.85","date":"2022/07/30","admin2":"Velikolepetian Settlement Community","admin3":"Región de Kherson","country_code":"UA","country_es":"Ucrania"}},{"type":"Feature","geometry":{"type":"Point","coordinates":[34.1364,47.0041]},"properties":{"bright":"342.75","date":"2022/07/30","admin2":"Comunidad rural de Rubanivska","admin3":"Región de Kherson","country_code":"UA","country_es":"Ucrania"}},{"type":"Feature","geometry":{"type":"Point","coordinates":[34.1303,47.0097]},"properties":{"bright":"340.65","date":"2022/07/30","admin2":"Comunidad rural de Rubanivska","admin3":"Región de Kherson","country_code":"UA","country_es":"Ucrania"}},{"type":"Feature","geometry":{"type":"Point","coordinates":[34.1538,47.0078]},"properties":{"bright":"325.79","date":"2022/07/30","admin2":"Comunidad rural de Rubanivska","admin3":"Región de Kherson","country_code":"UA","country_es":"Ucrania"}},{"type":"Feature","geometry":{"type":"Point","coordinates":[34.3011,46.4287]},"properties":{"bright":"326.46","date":"2022/07/30","admin2":"Novotroitskaya Community","admin3":"Región de Kherson","country_code":"UA","country_es":"Ucrania"}},{"type":"Feature","geometry":{"type":"Point","coordinates":[29.8007,45.67]},"properties":{"bright":"321.59","date":"2022/07/30","admin2":"Comunidad rural de Liman","admin3":"Región de ODESA","country_code":"UA","country_es":"Ucrania"}},{"type":"Feature","geometry":{"type":"Point","coordinates":[33.6581,50.0645]},"properties":{"bright":"306.79","date":"2022/07/30","admin2":"Comunidad de Mirgorod City","admin3":"Poltava","country_code":"UA","country_es":"Ucrania"}},{"type":"Feature","geometry":{"type":"Point","coordinates":[10.3371,36.4927]},"properties":{"bright":"358.78","date":"2022/07/30","admin2":"NA","admin3":"Delegación de marané","country_code":"TN","country_es":"Túnez"}},{"type":"Feature","geometry":{"type":"Point","coordinates":[10.3507,36.4911]},"properties":{"bright":"342.81","date":"2022/07/30","admin2":"NA","admin3":"Delegación de Qarbali","country_code":"TN","country_es":"Túnez"}},{"type":"Feature","geometry":{"type":"Point","coordinates":[10.3308,36.4912]},"properties":{"bright":"341.04","date":"2022/07/30","admin2":"NA","admin3":"Delegación de marané","country_code":"TN","country_es":"Túnez"}},{"type":"Feature","geometry":{"type":"Point","coordinates":[10.3444,36.4895]},"properties":{"bright":"365.99","date":"2022/07/30","admin2":"NA","admin3":"Delegación de marané","country_code":"TN","country_es":"Túnez"}},{"type":"Feature","geometry":{"type":"Point","coordinates":[28.2922,54.3326]},"properties":{"bright":"308.75","date":"2022/07/30","admin2":"Consejo de la aldea de Veselovsky","admin3":"Región de Minsk","country_code":"BY","country_es":"Bielorrusia"}},{"type":"Feature","geometry":{"type":"Point","coordinates":[23.0128,49.748]},"properties":{"bright":"310.95","date":"2022/07/30","admin2":"Comunidad del pueblo de Shehynivska","admin3":"Región de LVIV","country_code":"UA","country_es":"Ucrania"}},{"type":"Feature","geometry":{"type":"Point","coordinates":[32.9087,47.2573]},"properties":{"bright":"311.33","date":"2022/07/30","admin2":"Comunidad de asentamiento de Berezneguatsky","admin3":"Región mykolaiv","country_code":"UA","country_es":"Ucrania"}},{"type":"Feature","geometry":{"type":"Point","coordinates":[19.6406,44.4896]},"properties":{"bright":"340.41","date":"2022/07/30","admin2":"Municipio de Koceljeva","admin3":"Serbia central","country_code":"RS","country_es":"Serbia"}},{"type":"Feature","geometry":{"type":"Point","coordinates":[19.655,44.487]},"properties":{"bright":"322.65","date":"2022/07/30","admin2":"Municipio de Koceljeva","admin3":"Serbia central","country_code":"RS","country_es":"Serbia"}},{"type":"Feature","geometry":{"type":"Point","coordinates":[33.2461,35.0789]},"properties":{"bright":"334.94","date":"2022/07/30","admin2":"Necesitar","admin3":"Nicosia","country_code":"CY","country_es":"Chipre"}},{"type":"Feature","geometry":{"type":"Point","coordinates":[33.2332,35.0774]},"properties":{"bright":"334.30","date":"2022/07/30","admin2":"Necesitar","admin3":"Nicosia","country_code":"CY","country_es":"Chipre"}},{"type":"Feature","geometry":{"type":"Point","coordinates":[25.3437,42.8156]},"properties":{"bright":"314.69","date":"2022/07/30","admin2":"Gabrovo","admin3":"Gabrovo","country_code":"BG","country_es":"Bulgaria"}},{"type":"Feature","geometry":{"type":"Point","coordinates":[24.4799,43.3853]},"properties":{"bright":"325.67","date":"2022/07/30","admin2":"Pleven","admin3":"Pleven","country_code":"BG","country_es":"Bulgaria"}},{"type":"Feature","geometry":{"type":"Point","coordinates":[21.5161,44.1055]},"properties":{"bright":"323.65","date":"2022/07/30","admin2":"Municipio de despotovac","admin3":"Serbia central","country_code":"RS","country_es":"Serbia"}},{"type":"Feature","geometry":{"type":"Point","coordinates":[33.4706,46.128]},"properties":{"bright":"329.16","date":"2022/07/30","admin2":"Comunidad del pueblo de Kalanchatka","admin3":"Región de Kherson","country_code":"UA","country_es":"Ucrania"}},{"type":"Feature","geometry":{"type":"Point","coordinates":[34.9268,46.2543]},"properties":{"bright":"330.90","date":"2022/07/30","admin2":"Comunidad de la ciudad de Genichesk","admin3":"Región de Kherson","country_code":"UA","country_es":"Ucrania"}},{"type":"Feature","geometry":{"type":"Point","coordinates":[30.1636,45.9113]},"properties":{"bright":"328.52","date":"2022/07/30","admin2":"Comunidad de Tuzlovsk Village","admin3":"Región de ODESA","country_code":"UA","country_es":"Ucrania"}},{"type":"Feature","geometry":{"type":"Point","coordinates":[34.9771,46.3631]},"properties":{"bright":"327.13","date":"2022/07/30","admin2":"Comunidad de la ciudad de Genichesk","admin3":"Región de Kherson","country_code":"UA","country_es":"Ucrania"}},{"type":"Feature","geometry":{"type":"Point","coordinates":[33.8057,46.3134]},"properties":{"bright":"331.05","date":"2022/07/30","admin2":"Comunidad rural de Privaska","admin3":"Región de Kherson","country_code":"UA","country_es":"Ucrania"}},{"type":"Feature","geometry":{"type":"Point","coordinates":[34.7955,46.6183]},"properties":{"bright":"332.95","date":"2022/07/30","admin2":"Comunidad de asentamiento de Yakimovsky","admin3":"Región de Zaporizhzhia","country_code":"UA","country_es":"Ucrania"}},{"type":"Feature","geometry":{"type":"Point","coordinates":[34.7697,46.6165]},"properties":{"bright":"378.26","date":"2022/07/30","admin2":"Comunidad de asentamiento de Yakimovsky","admin3":"Región de Zaporizhzhia","country_code":"UA","country_es":"Ucrania"}},{"type":"Feature","geometry":{"type":"Point","coordinates":[34.7439,46.6146]},"properties":{"bright":"357.30","date":"2022/07/30","admin2":"Comunidad de asentamiento de Yakimovsky","admin3":"Región de Zaporizhzhia","country_code":"UA","country_es":"Ucrania"}},{"type":"Feature","geometry":{"type":"Point","coordinates":[34.7679,46.6288]},"properties":{"bright":"342.06","date":"2022/07/30","admin2":"Comunidad de asentamiento de Yakimovsky","admin3":"Región de Zaporizhzhia","country_code":"UA","country_es":"Ucrania"}},{"type":"Feature","geometry":{"type":"Point","coordinates":[34.7874,46.6217]},"properties":{"bright":"331.55","date":"2022/07/30","admin2":"Comunidad de asentamiento de Yakimovsky","admin3":"Región de Zaporizhzhia","country_code":"UA","country_es":"Ucrania"}},{"type":"Feature","geometry":{"type":"Point","coordinates":[34.7616,46.62]},"properties":{"bright":"377.95","date":"2022/07/30","admin2":"Comunidad de asentamiento de Yakimovsky","admin3":"Región de Zaporizhzhia","country_code":"UA","country_es":"Ucrania"}},{"type":"Feature","geometry":{"type":"Point","coordinates":[34.7597,46.6323]},"properties":{"bright":"336.09","date":"2022/07/30","admin2":"Comunidad de asentamiento de Yakimovsky","admin3":"Región de Zaporizhzhia","country_code":"UA","country_es":"Ucrania"}},{"type":"Feature","geometry":{"type":"Point","coordinates":[34.1362,46.6115]},"properties":{"bright":"329.26","date":"2022/07/30","admin2":"Novotroitskaya Community","admin3":"Región de Kherson","country_code":"UA","country_es":"Ucrania"}},{"type":"Feature","geometry":{"type":"Point","coordinates":[31.7852,46.5194]},"properties":{"bright":"323.69","date":"2022/07/30","admin2":"Comunidad de la ciudad de Ochakov","admin3":"Región mykolaiv","country_code":"UA","country_es":"Ucrania"}},{"type":"Feature","geometry":{"type":"Point","coordinates":[31.7672,46.5176]},"properties":{"bright":"365.51","date":"2022/07/30","admin2":"Comunidad de la ciudad de Ochakov","admin3":"Región mykolaiv","country_code":"UA","country_es":"Ucrania"}},{"type":"Feature","geometry":{"type":"Point","coordinates":[34.3253,46.776]},"properties":{"bright":"326.18","date":"2022/07/30","admin2":"Comunidad de asentamiento de Ivanivska","admin3":"Región de Kherson","country_code":"UA","country_es":"Ucrania"}},{"type":"Feature","geometry":{"type":"Point","coordinates":[32.4154,46.7391]},"properties":{"bright":"328.15","date":"2022/07/30","admin2":"Comunidad de la aldea de Chernobayiv","admin3":"Región de Kherson","country_code":"UA","country_es":"Ucrania"}},{"type":"Feature","geometry":{"type":"Point","coordinates":[32.7917,46.8642]},"properties":{"bright":"395.62","date":"2022/07/30","admin2":"Comunidad rural de Gorokhiv","admin3":"Región mykolaiv","country_code":"UA","country_es":"Ucrania"}},{"type":"Feature","geometry":{"type":"Point","coordinates":[32.7711,46.8624]},"properties":{"bright":"382.39","date":"2022/07/30","admin2":"Comunidad rural de Gorokhiv","admin3":"Región mykolaiv","country_code":"UA","country_es":"Ucrania"}},{"type":"Feature","geometry":{"type":"Point","coordinates":[32.7894,46.8752]},"properties":{"bright":"333.47","date":"2022/07/30","admin2":"Comunidad rural de Gorokhiv","admin3":"Región mykolaiv","country_code":"UA","country_es":"Ucrania"}},{"type":"Feature","geometry":{"type":"Point","coordinates":[32.7689,46.8734]},"properties":{"bright":"327.29","date":"2022/07/30","admin2":"Comunidad rural de Gorokhiv","admin3":"Región mykolaiv","country_code":"UA","country_es":"Ucrania"}},{"type":"Feature","geometry":{"type":"Point","coordinates":[32.5385,46.8974]},"properties":{"bright":"374.42","date":"2022/07/30","admin2":"Shevchenkivska Village Community","admin3":"Región mykolaiv","country_code":"UA","country_es":"Ucrania"}},{"type":"Feature","geometry":{"type":"Point","coordinates":[32.5186,46.8955]},"properties":{"bright":"335.29","date":"2022/07/30","admin2":"Shevchenkivska Village Community","admin3":"Región mykolaiv","country_code":"UA","country_es":"Ucrania"}},{"type":"Feature","geometry":{"type":"Point","coordinates":[32.5328,46.8981]},"properties":{"bright":"365.51","date":"2022/07/30","admin2":"Shevchenkivska Village Community","admin3":"Región mykolaiv","country_code":"UA","country_es":"Ucrania"}},{"type":"Feature","geometry":{"type":"Point","coordinates":[32.4167,47.0459]},"properties":{"bright":"337.04","date":"2022/07/30","admin2":"La comunidad de asentamientos de PervomaSky","admin3":"Región mykolaiv","country_code":"UA","country_es":"Ucrania"}},{"type":"Feature","geometry":{"type":"Point","coordinates":[32.3781,47.1799]},"properties":{"bright":"344.81","date":"2022/07/30","admin2":"Comunidad Rural Ingul","admin3":"Región mykolaiv","country_code":"UA","country_es":"Ucrania"}},{"type":"Feature","geometry":{"type":"Point","coordinates":[32.3582,47.1781]},"properties":{"bright":"328.92","date":"2022/07/30","admin2":"Comunidad Rural Ingul","admin3":"Región mykolaiv","country_code":"UA","country_es":"Ucrania"}},{"type":"Feature","geometry":{"type":"Point","coordinates":[33.8668,47.4757]},"properties":{"bright":"318.48","date":"2022/07/30","admin2":"Comunidad de asentamiento de novovorontsovsky","admin3":"Región de Kherson","country_code":"UA","country_es":"Ucrania"}},{"type":"Feature","geometry":{"type":"Point","coordinates":[33.8448,47.5653]},"properties":{"bright":"322.56","date":"2022/07/30","admin2":"Comunidad de la ciudad de Zelenodolsk","admin3":"Región de dnipropetrovsk","country_code":"UA","country_es":"Ucrania"}},{"type":"Feature","geometry":{"type":"Point","coordinates":[32.1745,49.7032]},"properties":{"bright":"313.90","date":"2022/07/30","admin2":"Comunidad del pueblo de Voznesensk","admin3":"Región cherkasy","country_code":"UA","country_es":"Ucrania"}},{"type":"Feature","geometry":{"type":"Point","coordinates":[33.6605,50.0702]},"properties":{"bright":"306.73","date":"2022/07/30","admin2":"Comunidad de Mirgorod City","admin3":"Poltava","country_code":"UA","country_es":"Ucrania"}},{"type":"Feature","geometry":{"type":"Point","coordinates":[31.7373,49.9266]},"properties":{"bright":"310.23","date":"2022/07/30","admin2":"Comunidad de Tsyblovsk Village","admin3":"Región de Kyiv","country_code":"UA","country_es":"Ucrania"}},{"type":"Feature","geometry":{"type":"Point","coordinates":[23.4606,49.574]},"properties":{"bright":"309.67","date":"2022/07/30","admin2":"Comunidad de la ciudad de Rudkiv","admin3":"Región de LVIV","country_code":"UA","country_es":"Ucrania"}},{"type":"Feature","geometry":{"type":"Point","coordinates":[34.9782,46.4797]},"properties":{"bright":"332.62","date":"2022/07/30","admin2":"Comunidad de la ciudad de Genichesk","admin3":"Región de Kherson","country_code":"UA","country_es":"Ucrania"}},{"type":"Feature","geometry":{"type":"Point","coordinates":[34.921,46.4623]},"properties":{"bright":"337.92","date":"2022/07/30","admin2":"Comunidad de la ciudad de Genichesk","admin3":"Región de Kherson","country_code":"UA","country_es":"Ucrania"}},{"type":"Feature","geometry":{"type":"Point","coordinates":[34.9709,46.478]},"properties":{"bright":"335.78","date":"2022/07/30","admin2":"Comunidad de la ciudad de Genichesk","admin3":"Región de Kherson","country_code":"UA","country_es":"Ucrania"}},{"type":"Feature","geometry":{"type":"Point","coordinates":[34.9138,46.4603]},"properties":{"bright":"331.60","date":"2022/07/30","admin2":"Comunidad de la ciudad de Genichesk","admin3":"Región de Kherson","country_code":"UA","country_es":"Ucrania"}},{"type":"Feature","geometry":{"type":"Point","coordinates":[10.3654,36.477]},"properties":{"bright":"335.12","date":"2022/07/30","admin2":"NA","admin3":"La delegación de hammamet","country_code":"TN","country_es":"Túnez"}},{"type":"Feature","geometry":{"type":"Point","coordinates":[10.3484,36.4753]},"properties":{"bright":"375.59","date":"2022/07/30","admin2":"NA","admin3":"Delegación zaguana","country_code":"TN","country_es":"Túnez"}},{"type":"Feature","geometry":{"type":"Point","coordinates":[10.3305,36.4735]},"properties":{"bright":"333.04","date":"2022/07/30","admin2":"NA","admin3":"Delegación zaguana","country_code":"TN","country_es":"Túnez"}},{"type":"Feature","geometry":{"type":"Point","coordinates":[10.3455,36.4861]},"properties":{"bright":"353.56","date":"2022/07/30","admin2":"NA","admin3":"Delegación zaguana","country_code":"TN","country_es":"Túnez"}},{"type":"Feature","geometry":{"type":"Point","coordinates":[25.5551,50.7426]},"properties":{"bright":"312.77","date":"2022/07/30","admin2":"Pidhaytsivska Comunidad rural","admin3":"Región de volin","country_code":"UA","country_es":"Ucrania"}},{"type":"Feature","geometry":{"type":"Point","coordinates":[34.9854,46.3785]},"properties":{"bright":"302.15","date":"2022/07/30","admin2":"Comunidad de la ciudad de Genichesk","admin3":"Región de Kherson","country_code":"UA","country_es":"Ucrania"}},{"type":"Feature","geometry":{"type":"Point","coordinates":[33.3605,46.1592]},"properties":{"bright":"309.99","date":"2022/07/30","admin2":"Comunidad del pueblo de Kalanchatka","admin3":"Región de Kherson","country_code":"UA","country_es":"Ucrania"}},{"type":"Feature","geometry":{"type":"Point","coordinates":[33.1438,46.1522]},"properties":{"bright":"300.62","date":"2022/07/30","admin2":"Comunidad de la ciudad de Skadovsk","admin3":"Región de Kherson","country_code":"UA","country_es":"Ucrania"}},{"type":"Feature","geometry":{"type":"Point","coordinates":[32.4508,46.1063]},"properties":{"bright":"303.89","date":"2022/07/30","admin2":"Comunidad rural de Bekhter","admin3":"Región de Kherson","country_code":"UA","country_es":"Ucrania"}},{"type":"Feature","geometry":{"type":"Point","coordinates":[34.9981,46.5958]},"properties":{"bright":"303.33","date":"2022/07/30","admin2":"Comunidad de asentamiento de Yakimovsky","admin3":"Región de Zaporizhzhia","country_code":"UA","country_es":"Ucrania"}},{"type":"Feature","geometry":{"type":"Point","coordinates":[34.7668,46.5964]},"properties":{"bright":"305.12","date":"2022/07/30","admin2":"Comunidad de asentamiento de Yakimovsky","admin3":"Región de Zaporizhzhia","country_code":"UA","country_es":"Ucrania"}},{"type":"Feature","geometry":{"type":"Point","coordinates":[34.7697,46.6131]},"properties":{"bright":"302.79","date":"2022/07/30","admin2":"Comunidad de asentamiento de Yakimovsky","admin3":"Región de Zaporizhzhia","country_code":"UA","country_es":"Ucrania"}},{"type":"Feature","geometry":{"type":"Point","coordinates":[34.7665,46.6221]},"properties":{"bright":"304.49","date":"2022/07/30","admin2":"Comunidad de asentamiento de Yakimovsky","admin3":"Región de Zaporizhzhia","country_code":"UA","country_es":"Ucrania"}},{"type":"Feature","geometry":{"type":"Point","coordinates":[34.3013,46.6026]},"properties":{"bright":"307.45","date":"2022/07/30","admin2":"Comunidad de asentamiento de Ivanivska","admin3":"Región de Kherson","country_code":"UA","country_es":"Ucrania"}},{"type":"Feature","geometry":{"type":"Point","coordinates":[33.8569,46.7678]},"properties":{"bright":"300.05","date":"2022/07/30","admin2":"Comunidad de la aldea de Konstantinovsk","admin3":"Región de Kherson","country_code":"UA","country_es":"Ucrania"}},{"type":"Feature","geometry":{"type":"Point","coordinates":[33.8479,46.8598]},"properties":{"bright":"306.66","date":"2022/07/30","admin2":"Comunidad de la aldea de Konstantinovsk","admin3":"Región de Kherson","country_code":"UA","country_es":"Ucrania"}},{"type":"Feature","geometry":{"type":"Point","coordinates":[31.7843,46.5033]},"properties":{"bright":"320.97","date":"2022/07/30","admin2":"Comunidad de la ciudad de Ochakov","admin3":"Región mykolaiv","country_code":"UA","country_es":"Ucrania"}},{"type":"Feature","geometry":{"type":"Point","coordinates":[31.7801,46.5134]},"properties":{"bright":"318.18","date":"2022/07/30","admin2":"Comunidad de la ciudad de Ochakov","admin3":"Región mykolaiv","country_code":"UA","country_es":"Ucrania"}},{"type":"Feature","geometry":{"type":"Point","coordinates":[31.7626,46.5101]},"properties":{"bright":"309.05","date":"2022/07/30","admin2":"Comunidad de la ciudad de Ochakov","admin3":"Región mykolaiv","country_code":"UA","country_es":"Ucrania"}},{"type":"Feature","geometry":{"type":"Point","coordinates":[32.8983,46.8056]},"properties":{"bright":"302.97","date":"2022/07/30","admin2":"Comunidad de la aldea de Daryevskaya","admin3":"Región de Kherson","country_code":"UA","country_es":"Ucrania"}},{"type":"Feature","geometry":{"type":"Point","coordinates":[32.4146,46.7274]},"properties":{"bright":"303.49","date":"2022/07/30","admin2":"Comunidad de la aldea de Chernobayiv","admin3":"Región de Kherson","country_code":"UA","country_es":"Ucrania"}},{"type":"Feature","geometry":{"type":"Point","coordinates":[34.3733,47.1263]},"properties":{"bright":"301.73","date":"2022/07/30","admin2":"Comunidad de asentamiento de Verkhnorogachytska","admin3":"Región de Kherson","country_code":"UA","country_es":"Ucrania"}},{"type":"Feature","geometry":{"type":"Point","coordinates":[32.6952,46.9044]},"properties":{"bright":"301.60","date":"2022/07/30","admin2":"Comunidad rural de Gorokhiv","admin3":"Región mykolaiv","country_code":"UA","country_es":"Ucrania"}},{"type":"Feature","geometry":{"type":"Point","coordinates":[34.5334,47.2367]},"properties":{"bright":"302.63","date":"2022/07/30","admin2":"La gran comunidad rural de Bilozersk","admin3":"Región de Zaporizhzhia","country_code":"UA","country_es":"Ucrania"}},{"type":"Feature","geometry":{"type":"Point","coordinates":[34.5301,47.2458]},"properties":{"bright":"305.19","date":"2022/07/30","admin2":"La gran comunidad rural de Bilozersk","admin3":"Región de Zaporizhzhia","country_code":"UA","country_es":"Ucrania"}},{"type":"Feature","geometry":{"type":"Point","coordinates":[32.2176,46.8786]},"properties":{"bright":"300.90","date":"2022/07/30","admin2":"Shevchenkivska Village Community","admin3":"Región mykolaiv","country_code":"UA","country_es":"Ucrania"}},{"type":"Feature","geometry":{"type":"Point","coordinates":[32.8999,47.2339]},"properties":{"bright":"302.01","date":"2022/07/30","admin2":"Comunidad de asentamiento de Berezneguatsky","admin3":"Región mykolaiv","country_code":"UA","country_es":"Ucrania"}},{"type":"Feature","geometry":{"type":"Point","coordinates":[34.3203,47.6326]},"properties":{"bright":"300.35","date":"2022/07/30","admin2":"Comunidad del pueblo de Pokrovsk","admin3":"Región de dnipropetrovsk","country_code":"UA","country_es":"Ucrania"}},{"type":"Feature","geometry":{"type":"Point","coordinates":[31.578,47.4675]},"properties":{"bright":"301.14","date":"2022/07/30","admin2":"Doroshevsk Village Community","admin3":"Región mykolaiv","country_code":"UA","country_es":"Ucrania"}},{"type":"Feature","geometry":{"type":"Point","coordinates":[31.6397,47.9507]},"properties":{"bright":"303.52","date":"2022/07/30","admin2":"Comunidad de asentamiento fraternal","admin3":"Región mykolaiv","country_code":"UA","country_es":"Ucrania"}},{"type":"Feature","geometry":{"type":"Point","coordinates":[30.8726,48.1405]},"properties":{"bright":"304.46","date":"2022/07/30","admin2":"Sinyukhinobrida comunidad rural","admin3":"Región mykolaiv","country_code":"UA","country_es":"Ucrania"}},{"type":"Feature","geometry":{"type":"Point","coordinates":[30.8651,48.1453]},"properties":{"bright":"305.01","date":"2022/07/30","admin2":"Sinyukhinobrida comunidad rural","admin3":"Región mykolaiv","country_code":"UA","country_es":"Ucrania"}},{"type":"Feature","geometry":{"type":"Point","coordinates":[30.9645,48.3472]},"properties":{"bright":"308.79","date":"2022/07/30","admin2":"Comunidad de asentamiento de Vilshansk","admin3":"Región de Kirovohrad","country_code":"UA","country_es":"Ucrania"}},{"type":"Feature","geometry":{"type":"Point","coordinates":[29.9838,52.8489]},"properties":{"bright":"308.01","date":"2022/07/30","admin2":"Consejo de la aldea de Solonsky","admin3":"Región de Gomel","country_code":"BY","country_es":"Bielorrusia"}},{"type":"Feature","geometry":{"type":"Point","coordinates":[10.3385,36.4813]},"properties":{"bright":"308.15","date":"2022/07/30","admin2":"NA","admin3":"Delegación zaguana","country_code":"TN","country_es":"Túnez"}},{"type":"Feature","geometry":{"type":"Point","coordinates":[10.3393,36.4771]},"properties":{"bright":"306.27","date":"2022/07/31","admin2":"NA","admin3":"Delegación zaguana","country_code":"TN","country_es":"Túnez"}},{"type":"Feature","geometry":{"type":"Point","coordinates":[-5.5063,35.2604]},"properties":{"bright":"305.73","date":"2022/07/31","admin2":"Caïdat por bni aârouss","admin3":"Provincia de Larache Región de Larache","country_code":"MA","country_es":"Marruecos"}}]}